<?xml version="1.0" encoding="UTF-8"?>
<billStatus>
  <bill>
    <calendarNumbers />
    <billType>S</billType>
    <notes />
    <subjects>
      <billSubjects>
        <policyArea>
          <name>Labor and Employment</name>
        </policyArea>
        <legislativeSubjects />
      </billSubjects>
    </subjects>
    <updateDate>2017-09-29T16:58:42Z</updateDate>
    <policyArea>
      <name>Labor and Employment</name>
    </policyArea>
    <introducedDate>2017-09-19</introducedDate>
    <recordedVotes />
    <committees>
      <billCommittees>
        <item>
          <type>Standing</type>
          <chamber>Senate</chamber>
          <systemCode>sshr00</systemCode>
          <activities>
            <item>
              <date>2017-09-19T21:16:18Z</date>
              <name>Referred to</name>
            </item>
          </activities>
          <name>Health, Education, Labor, and Pensions Committee</name>
          <subcommittees />
        </item>
      </billCommittees>
    </committees>
    <cosponsors>
      <item>
        <firstName>SHERROD</firstName>
        <identifiers>
          <bioguideId>B000944</bioguideId>
          <gpoId>8309</gpoId>
          <lisID>136</lisID>
        </identifiers>
        <sponsorshipDate>2017-09-19</sponsorshipDate>
        <state>OH</state>
        <fullName>Sen. Brown, Sherrod [D-OH]</fullName>
        <bioguideId>B000944</bioguideId>
        <isOriginalCosponsor>True</isOriginalCosponsor>
        <middleName />
        <sponsorshipWithdrawnDate />
        <party>D</party>
        <lastName>BROWN</lastName>
      </item>
      <item>
        <firstName>Kirsten</firstName>
        <identifiers>
          <bioguideId>G000555</bioguideId>
          <gpoId>8336</gpoId>
          <lisID>1866</lisID>
        </identifiers>
        <sponsorshipDate>2017-09-19</sponsorshipDate>
        <state>NY</state>
        <fullName>Sen. Gillibrand, Kirsten E. [D-NY]</fullName>
        <bioguideId>G000555</bioguideId>
        <isOriginalCosponsor>True</isOriginalCosponsor>
        <middleName>E.</middleName>
        <sponsorshipWithdrawnDate />
        <party>D</party>
        <lastName>Gillibrand</lastName>
      </item>
      <item>
        <firstName>TAMMY</firstName>
        <identifiers>
          <gpoId>8215</gpoId>
          <bioguideId>B001230</bioguideId>
          <lisID>1558</lisID>
        </identifiers>
        <sponsorshipDate>2017-09-19</sponsorshipDate>
        <state>WI</state>
        <fullName>Sen. Baldwin, Tammy [D-WI]</fullName>
        <bioguideId>B001230</bioguideId>
        <isOriginalCosponsor>True</isOriginalCosponsor>
        <middleName />
        <sponsorshipWithdrawnDate />
        <party>D</party>
        <lastName>BALDWIN</lastName>
      </item>
      <item>
        <firstName>Jeff</firstName>
        <identifiers>
          <lisID>1900</lisID>
          <bioguideId>M001176</bioguideId>
          <gpoId>8238</gpoId>
        </identifiers>
        <sponsorshipDate>2017-09-19</sponsorshipDate>
        <state>OR</state>
        <fullName>Sen. Merkley, Jeff [D-OR]</fullName>
        <bioguideId>M001176</bioguideId>
        <isOriginalCosponsor>True</isOriginalCosponsor>
        <middleName />
        <sponsorshipWithdrawnDate />
        <party>D</party>
        <lastName>Merkley</lastName>
      </item>
      <item>
        <firstName>EDWARD</firstName>
        <identifiers>
          <gpoId>7972</gpoId>
          <lisID>735</lisID>
          <bioguideId>M000133</bioguideId>
        </identifiers>
        <sponsorshipDate>2017-09-19</sponsorshipDate>
        <state>MA</state>
        <fullName>Sen. Markey, Edward J. [D-MA]</fullName>
        <bioguideId>M000133</bioguideId>
        <isOriginalCosponsor>True</isOriginalCosponsor>
        <middleName>J.</middleName>
        <sponsorshipWithdrawnDate />
        <party>D</party>
        <lastName>MARKEY</lastName>
      </item>
      <item>
        <firstName>Margaret</firstName>
        <identifiers>
          <bioguideId>H001076</bioguideId>
          <lisID>2302</lisID>
          <gpoId />
        </identifiers>
        <sponsorshipDate>2017-09-19</sponsorshipDate>
        <state>NH</state>
        <fullName>Sen. Hassan, Margaret Wood [D-NH]</fullName>
        <bioguideId>H001076</bioguideId>
        <isOriginalCosponsor>True</isOriginalCosponsor>
        <middleName>Wood</middleName>
        <sponsorshipWithdrawnDate />
        <party>D</party>
        <lastName>Hassan</lastName>
      </item>
    </cosponsors>
    <laws />
    <originChamber>Senate</originChamber>
    <committeeReports />
    <titles>
      <item>
        <parentTitleType />
        <chamberName />
        <title>Protecting Workers and Improving Labor Standards Act</title>
        <chamberCode />
        <titleType>Short Titles as Introduced</titleType>
      </item>
      <item>
        <parentTitleType />
        <chamberName />
        <title>A bill to repeal the authority under the National Labor Relations Act for States to enact laws prohibiting agreements requiring membership in a labor organization as a condition of employment, and for other purposes.</title>
        <chamberCode />
        <titleType>Official Title as Introduced</titleType>
      </item>
      <item>
        <parentTitleType />
        <chamberName />
        <title>Protecting Workers and Improving Labor Standards Act</title>
        <chamberCode />
        <titleType>Display Title</titleType>
      </item>
      <item>
        <parentTitleType />
        <chamberName />
        <title>Protecting Workers and Improving Labor Standards Act</title>
        <chamberCode />
        <titleType>(Extracted from GPO) Short Titles as Introduced</titleType>
      </item>
    </titles>
    <version>1.0.0</version>
    <sponsors>
      <item>
        <fullName>Sen. Warren, Elizabeth [D-MA]</fullName>
        <lastName>Warren</lastName>
        <bioguideId>W000817</bioguideId>
        <party>D</party>
        <firstName>Elizabeth</firstName>
        <middleName>A.</middleName>
        <state>MA</state>
        <byRequestType />
        <identifiers>
          <lisID>2182</lisID>
          <gpoId />
          <bioguideId>W000817</bioguideId>
        </identifiers>
      </item>
    </sponsors>
    <cboCostEstimates />
    <latestAction>
      <actionDate>2017-09-19</actionDate>
      <text>Read twice and referred to the Committee on Health, Education, Labor, and Pensions.</text>
      <links />
    </latestAction>
    <title>Protecting Workers and Improving Labor Standards Act</title>
    <congress>115</congress>
    <createDate>2017-09-20T00:41:19Z</createDate>
    <relatedBills />
    <summaries>
      <billSummaries />
    </summaries>
    <actions>
      <item>
        <actionDate>2017-09-19</actionDate>
        <committee>
          <name>Health, Education, Labor, and Pensions Committee</name>
          <systemCode>sshr00</systemCode>
        </committee>
        <links />
        <sourceSystem>
          <name>Senate</name>
          <code>0</code>
        </sourceSystem>
        <text>Read twice and referred to the Committee on Health, Education, Labor, and Pensions.</text>
        <type>IntroReferral</type>
      </item>
      <item>
        <text>Introduced in Senate</text>
        <sourceSystem>
          <name>Library of Congress</name>
          <code>9</code>
        </sourceSystem>
        <links />
        <actionCode>10000</actionCode>
        <actionDate>2017-09-19</actionDate>
        <type>IntroReferral</type>
        <committee />
      </item>
      <actionTypeCounts>
        <referredToCommittee>1</referredToCommittee>
        <introducedInSenate>1</introducedInSenate>
      </actionTypeCounts>
      <actionByCounts>
        <senate>2</senate>
      </actionByCounts>
    </actions>
    <amendments />
    <billNumber>1838</billNumber>
  </bill>
  <dublinCore xmlns:dc="http://purl.org/dc/elements/1.1/">
    <dc:format>text/xml</dc:format>
    <dc:language>EN</dc:language>
    <dc:rights>Pursuant to Title 17 Section 105 of the United States Code, this file is not subject to copyright protection and is in the public domain.</dc:rights>
    <dc:contributor>Congressional Research Service, Library of Congress</dc:contributor>
    <dc:description>This file contains bill summaries and statuses for federal legislation. A bill summary describes the most significant provisions of a piece of legislation and details the effects the legislative text may have on current law and federal programs. Bill summaries are authored by the Congressional Research Service (CRS) of the Library of Congress. As stated in Public Law 91-510 (2 USC 166 (d)(6)), one of the duties of CRS is "to prepare summaries and digests of bills and resolutions of a public general nature introduced in the Senate or House of Representatives". For more information, refer to the User Guide that accompanies this file.</dc:description>
  </dublinCore>
</billStatus>

