<?xml version="1.0" encoding="UTF-8"?>
<billStatus>
  <bill>
    <recordedVotes />
    <cosponsors>
      <item>
        <identifiers>
          <gpoId>8244</gpoId>
          <lisID>1383</lisID>
          <bioguideId>L000174</bioguideId>
        </identifiers>
        <sponsorshipWithdrawnDate />
        <party>D</party>
        <bioguideId>L000174</bioguideId>
        <state>VT</state>
        <middleName>JOSEPH</middleName>
        <fullName>Sen. Leahy, Patrick J. [D-VT]</fullName>
        <isOriginalCosponsor>True</isOriginalCosponsor>
        <firstName>PATRICK</firstName>
        <sponsorshipDate>2017-05-25</sponsorshipDate>
        <lastName>LEAHY</lastName>
      </item>
      <item>
        <identifiers>
          <gpoId>8307</gpoId>
          <bioguideId>M000934</bioguideId>
          <lisID>1507</lisID>
        </identifiers>
        <sponsorshipWithdrawnDate />
        <party>R</party>
        <bioguideId>M000934</bioguideId>
        <state>KS</state>
        <middleName />
        <fullName>Sen. Moran, Jerry [R-KS]</fullName>
        <isOriginalCosponsor>True</isOriginalCosponsor>
        <firstName>JERRY</firstName>
        <sponsorshipDate>2017-05-25</sponsorshipDate>
        <lastName>MORAN</lastName>
      </item>
      <item>
        <identifiers>
          <bioguideId>D000563</bioguideId>
          <lisID>326</lisID>
          <gpoId>8326</gpoId>
        </identifiers>
        <sponsorshipWithdrawnDate />
        <party>D</party>
        <bioguideId>D000563</bioguideId>
        <state>IL</state>
        <middleName>J.</middleName>
        <fullName>Sen. Durbin, Richard J. [D-IL]</fullName>
        <isOriginalCosponsor>True</isOriginalCosponsor>
        <firstName>RICHARD</firstName>
        <sponsorshipDate>2017-05-25</sponsorshipDate>
        <lastName>DURBIN</lastName>
      </item>
      <item>
        <identifiers>
          <lisID>1542</lisID>
          <gpoId>8328</gpoId>
          <bioguideId>E000285</bioguideId>
        </identifiers>
        <sponsorshipWithdrawnDate />
        <party>R</party>
        <bioguideId>E000285</bioguideId>
        <state>WY</state>
        <middleName>B.</middleName>
        <fullName>Sen. Enzi, Michael B. [R-WY]</fullName>
        <isOriginalCosponsor>True</isOriginalCosponsor>
        <firstName>MICHAEL</firstName>
        <sponsorshipDate>2017-05-25</sponsorshipDate>
        <lastName>ENZI</lastName>
      </item>
      <item>
        <identifiers>
          <gpoId>8260</gpoId>
          <lisID>1567</lisID>
          <bioguideId>U000039</bioguideId>
        </identifiers>
        <sponsorshipWithdrawnDate />
        <party>D</party>
        <bioguideId>U000039</bioguideId>
        <state>NM</state>
        <middleName />
        <fullName>Sen. Udall, Tom [D-NM]</fullName>
        <isOriginalCosponsor>True</isOriginalCosponsor>
        <firstName>TOM</firstName>
        <sponsorshipDate>2017-05-25</sponsorshipDate>
        <lastName>UDALL</lastName>
      </item>
      <item>
        <identifiers>
          <lisID>1687</lisID>
          <gpoId>8247</gpoId>
          <bioguideId>B001236</bioguideId>
        </identifiers>
        <sponsorshipWithdrawnDate />
        <party>R</party>
        <bioguideId>B001236</bioguideId>
        <state>AR</state>
        <middleName />
        <fullName>Sen. Boozman, John [R-AR]</fullName>
        <isOriginalCosponsor>True</isOriginalCosponsor>
        <firstName>John</firstName>
        <sponsorshipDate>2017-05-25</sponsorshipDate>
        <lastName>Boozman</lastName>
      </item>
      <item>
        <identifiers>
          <lisID>1823</lisID>
          <gpoId>8264</gpoId>
          <bioguideId>W000802</bioguideId>
        </identifiers>
        <sponsorshipWithdrawnDate />
        <party>D</party>
        <bioguideId>W000802</bioguideId>
        <state>RI</state>
        <middleName />
        <fullName>Sen. Whitehouse, Sheldon [D-RI]</fullName>
        <isOriginalCosponsor>True</isOriginalCosponsor>
        <firstName>Sheldon</firstName>
        <sponsorshipDate>2017-05-25</sponsorshipDate>
        <lastName>Whitehouse</lastName>
      </item>
      <item>
        <identifiers>
          <bioguideId>C001035</bioguideId>
          <lisID>1541</lisID>
          <gpoId>8291</gpoId>
        </identifiers>
        <sponsorshipWithdrawnDate />
        <party>R</party>
        <bioguideId>C001035</bioguideId>
        <state>ME</state>
        <middleName>MARGARET</middleName>
        <fullName>Sen. Collins, Susan M. [R-ME]</fullName>
        <isOriginalCosponsor>True</isOriginalCosponsor>
        <firstName>SUSAN</firstName>
        <sponsorshipDate>2017-05-25</sponsorshipDate>
        <lastName>COLLINS</lastName>
      </item>
      <item>
        <identifiers>
          <bioguideId>K000367</bioguideId>
          <lisID>1826</lisID>
          <gpoId>8249</gpoId>
        </identifiers>
        <sponsorshipWithdrawnDate />
        <party>D</party>
        <bioguideId>K000367</bioguideId>
        <state>MN</state>
        <middleName />
        <fullName>Sen. Klobuchar, Amy [D-MN]</fullName>
        <isOriginalCosponsor>True</isOriginalCosponsor>
        <firstName>Amy</firstName>
        <sponsorshipDate>2017-05-25</sponsorshipDate>
        <lastName>Klobuchar</lastName>
      </item>
      <item>
        <identifiers>
          <lisID>1900</lisID>
          <gpoId>8238</gpoId>
          <bioguideId>M001176</bioguideId>
        </identifiers>
        <sponsorshipWithdrawnDate />
        <party>D</party>
        <bioguideId>M001176</bioguideId>
        <state>OR</state>
        <middleName />
        <fullName>Sen. Merkley, Jeff [D-OR]</fullName>
        <isOriginalCosponsor>True</isOriginalCosponsor>
        <firstName>Jeff</firstName>
        <sponsorshipDate>2017-05-25</sponsorshipDate>
        <lastName>Merkley</lastName>
      </item>
      <item>
        <identifiers>
          <bioguideId>R000122</bioguideId>
          <lisID>949</lisID>
          <gpoId>8272</gpoId>
        </identifiers>
        <sponsorshipWithdrawnDate />
        <party>D</party>
        <bioguideId>R000122</bioguideId>
        <state>RI</state>
        <middleName>F.</middleName>
        <fullName>Sen. Reed, Jack [D-RI]</fullName>
        <isOriginalCosponsor>True</isOriginalCosponsor>
        <firstName>JOHN</firstName>
        <sponsorshipDate>2017-05-25</sponsorshipDate>
        <lastName>REED</lastName>
      </item>
      <item>
        <identifiers>
          <lisID>1531</lisID>
          <gpoId>8261</gpoId>
          <bioguideId>S000770</bioguideId>
        </identifiers>
        <sponsorshipWithdrawnDate />
        <party>D</party>
        <bioguideId>S000770</bioguideId>
        <state>MI</state>
        <middleName>ANN</middleName>
        <fullName>Sen. Stabenow, Debbie [D-MI]</fullName>
        <isOriginalCosponsor>True</isOriginalCosponsor>
        <firstName>DEBORAH</firstName>
        <sponsorshipDate>2017-05-25</sponsorshipDate>
        <lastName>STABENOW</lastName>
      </item>
      <item>
        <identifiers>
          <lisID>1837</lisID>
          <gpoId>7870</gpoId>
          <bioguideId>M001169</bioguideId>
        </identifiers>
        <sponsorshipWithdrawnDate />
        <party>D</party>
        <bioguideId>M001169</bioguideId>
        <state>CT</state>
        <middleName />
        <fullName>Sen. Murphy, Christopher [D-CT]</fullName>
        <isOriginalCosponsor>True</isOriginalCosponsor>
        <firstName>Christopher</firstName>
        <sponsorshipDate>2017-05-25</sponsorshipDate>
        <lastName>Murphy</lastName>
      </item>
      <item>
        <identifiers>
          <lisID>1984</lisID>
          <gpoId>8297</gpoId>
          <bioguideId>C001088</bioguideId>
        </identifiers>
        <sponsorshipWithdrawnDate />
        <party>D</party>
        <bioguideId>C001088</bioguideId>
        <state>DE</state>
        <middleName>A.</middleName>
        <fullName>Sen. Coons, Christopher A. [D-DE]</fullName>
        <isOriginalCosponsor>True</isOriginalCosponsor>
        <firstName>Christopher</firstName>
        <sponsorshipDate>2017-05-25</sponsorshipDate>
        <lastName>Coons</lastName>
      </item>
      <item>
        <identifiers>
          <lisID>174</lisID>
          <gpoId>8287</gpoId>
          <bioguideId>C000141</bioguideId>
        </identifiers>
        <sponsorshipWithdrawnDate />
        <party>D</party>
        <bioguideId>C000141</bioguideId>
        <state>MD</state>
        <middleName>L.</middleName>
        <fullName>Sen. Cardin, Benjamin L. [D-MD]</fullName>
        <isOriginalCosponsor>True</isOriginalCosponsor>
        <firstName>BENJAMIN</firstName>
        <sponsorshipDate>2017-05-25</sponsorshipDate>
        <lastName>CARDIN</lastName>
      </item>
      <item>
        <identifiers>
          <lisID>1332</lisID>
          <gpoId>8338</gpoId>
          <bioguideId>F000062</bioguideId>
        </identifiers>
        <sponsorshipWithdrawnDate />
        <party>D</party>
        <bioguideId>F000062</bioguideId>
        <state>CA</state>
        <middleName />
        <fullName>Sen. Feinstein, Dianne [D-CA]</fullName>
        <isOriginalCosponsor>True</isOriginalCosponsor>
        <firstName>DIANNE</firstName>
        <sponsorshipDate>2017-05-25</sponsorshipDate>
        <lastName>FEINSTEIN</lastName>
      </item>
      <item>
        <identifiers>
          <lisID>1901</lisID>
          <gpoId>8276</gpoId>
          <bioguideId>S001181</bioguideId>
        </identifiers>
        <sponsorshipWithdrawnDate />
        <party>D</party>
        <bioguideId>S001181</bioguideId>
        <state>NH</state>
        <middleName />
        <fullName>Sen. Shaheen, Jeanne [D-NH]</fullName>
        <isOriginalCosponsor>True</isOriginalCosponsor>
        <firstName>Jeanne</firstName>
        <sponsorshipDate>2017-05-25</sponsorshipDate>
        <lastName>Shaheen</lastName>
      </item>
      <item>
        <identifiers>
          <lisID>2174</lisID>
          <gpoId />
          <bioguideId>H001069</bioguideId>
        </identifiers>
        <sponsorshipWithdrawnDate />
        <party>D</party>
        <bioguideId>H001069</bioguideId>
        <state>ND</state>
        <middleName />
        <fullName>Sen. Heitkamp, Heidi [D-ND]</fullName>
        <isOriginalCosponsor>True</isOriginalCosponsor>
        <firstName>Heidi</firstName>
        <sponsorshipDate>2017-05-25</sponsorshipDate>
        <lastName>Heitkamp</lastName>
      </item>
      <item>
        <identifiers>
          <gpoId>8309</gpoId>
          <lisID>136</lisID>
          <bioguideId>B000944</bioguideId>
        </identifiers>
        <sponsorshipWithdrawnDate />
        <party>D</party>
        <bioguideId>B000944</bioguideId>
        <state>OH</state>
        <middleName />
        <fullName>Sen. Brown, Sherrod [D-OH]</fullName>
        <isOriginalCosponsor>True</isOriginalCosponsor>
        <firstName>SHERROD</firstName>
        <sponsorshipDate>2017-05-25</sponsorshipDate>
        <lastName>BROWN</lastName>
      </item>
      <item>
        <identifiers>
          <gpoId>8215</gpoId>
          <bioguideId>B001230</bioguideId>
          <lisID>1558</lisID>
        </identifiers>
        <sponsorshipWithdrawnDate />
        <party>D</party>
        <bioguideId>B001230</bioguideId>
        <state>WI</state>
        <middleName />
        <fullName>Sen. Baldwin, Tammy [D-WI]</fullName>
        <isOriginalCosponsor>True</isOriginalCosponsor>
        <firstName>TAMMY</firstName>
        <sponsorshipDate>2017-05-25</sponsorshipDate>
        <lastName>BALDWIN</lastName>
      </item>
      <item>
        <identifiers>
          <bioguideId>H001042</bioguideId>
          <gpoId>7913</gpoId>
          <lisID>1844</lisID>
        </identifiers>
        <sponsorshipWithdrawnDate />
        <party>D</party>
        <bioguideId>H001042</bioguideId>
        <state>HI</state>
        <middleName>K.</middleName>
        <fullName>Sen. Hirono, Mazie K. [D-HI]</fullName>
        <isOriginalCosponsor>True</isOriginalCosponsor>
        <firstName>Mazie</firstName>
        <sponsorshipDate>2017-05-25</sponsorshipDate>
        <lastName>Hirono</lastName>
      </item>
      <item>
        <identifiers>
          <bioguideId>S001194</bioguideId>
          <lisID>2173</lisID>
          <gpoId />
        </identifiers>
        <sponsorshipWithdrawnDate />
        <party>D</party>
        <bioguideId>S001194</bioguideId>
        <state>HI</state>
        <middleName />
        <fullName>Sen. Schatz, Brian [D-HI]</fullName>
        <isOriginalCosponsor>True</isOriginalCosponsor>
        <firstName>Brian</firstName>
        <sponsorshipDate>2017-05-25</sponsorshipDate>
        <lastName>Schatz</lastName>
      </item>
      <item>
        <identifiers>
          <lisID>735</lisID>
          <gpoId>7972</gpoId>
          <bioguideId>M000133</bioguideId>
        </identifiers>
        <sponsorshipWithdrawnDate />
        <party>D</party>
        <bioguideId>M000133</bioguideId>
        <state>MA</state>
        <middleName>J.</middleName>
        <fullName>Sen. Markey, Edward J. [D-MA]</fullName>
        <isOriginalCosponsor>True</isOriginalCosponsor>
        <firstName>EDWARD</firstName>
        <sponsorshipDate>2017-05-25</sponsorshipDate>
        <lastName>MARKEY</lastName>
      </item>
      <item>
        <identifiers>
          <bioguideId>M001170</bioguideId>
          <gpoId>8252</gpoId>
          <lisID>1820</lisID>
        </identifiers>
        <sponsorshipWithdrawnDate />
        <party>D</party>
        <bioguideId>M001170</bioguideId>
        <state>MO</state>
        <middleName />
        <fullName>Sen. McCaskill, Claire [D-MO]</fullName>
        <isOriginalCosponsor>True</isOriginalCosponsor>
        <firstName>Claire</firstName>
        <sponsorshipDate>2017-05-25</sponsorshipDate>
        <lastName>McCaskill</lastName>
      </item>
      <item>
        <identifiers>
          <lisID>2082</lisID>
          <gpoId>8308</gpoId>
          <bioguideId>P000603</bioguideId>
        </identifiers>
        <sponsorshipWithdrawnDate />
        <party>R</party>
        <bioguideId>P000603</bioguideId>
        <state>KY</state>
        <middleName />
        <fullName>Sen. Paul, Rand [R-KY]</fullName>
        <isOriginalCosponsor>True</isOriginalCosponsor>
        <firstName>Rand</firstName>
        <sponsorshipDate>2017-05-25</sponsorshipDate>
        <lastName>Paul</lastName>
      </item>
      <item>
        <identifiers>
          <lisID>1247</lisID>
          <gpoId>8265</gpoId>
          <bioguideId>W000779</bioguideId>
        </identifiers>
        <sponsorshipWithdrawnDate />
        <party>D</party>
        <bioguideId>W000779</bioguideId>
        <state>OR</state>
        <middleName />
        <fullName>Sen. Wyden, Ron [D-OR]</fullName>
        <isOriginalCosponsor>True</isOriginalCosponsor>
        <firstName>RON</firstName>
        <sponsorshipDate>2017-05-25</sponsorshipDate>
        <lastName>WYDEN</lastName>
      </item>
      <item>
        <identifiers>
          <lisID>2176</lisID>
          <gpoId />
          <bioguideId>K000384</bioguideId>
        </identifiers>
        <sponsorshipWithdrawnDate />
        <party>D</party>
        <bioguideId>K000384</bioguideId>
        <state>VA</state>
        <middleName />
        <fullName>Sen. Kaine, Tim [D-VA]</fullName>
        <isOriginalCosponsor>True</isOriginalCosponsor>
        <firstName>Timothy</firstName>
        <sponsorshipDate>2017-05-25</sponsorshipDate>
        <lastName>Kaine</lastName>
      </item>
      <item>
        <identifiers>
          <lisID>2185</lisID>
          <gpoId />
          <bioguideId>K000383</bioguideId>
        </identifiers>
        <sponsorshipWithdrawnDate />
        <party>I</party>
        <bioguideId>K000383</bioguideId>
        <state>ME</state>
        <middleName />
        <fullName>Sen. King, Angus S., Jr. [I-ME]</fullName>
        <isOriginalCosponsor>True</isOriginalCosponsor>
        <firstName>Angus</firstName>
        <sponsorshipDate>2017-05-25</sponsorshipDate>
        <lastName>King</lastName>
      </item>
      <item>
        <identifiers>
          <gpoId>8339</gpoId>
          <bioguideId>F000457</bioguideId>
          <lisID>1969</lisID>
        </identifiers>
        <sponsorshipWithdrawnDate />
        <party>D</party>
        <bioguideId>F000457</bioguideId>
        <state>MN</state>
        <middleName />
        <fullName>Sen. Franken, Al [D-MN]</fullName>
        <isOriginalCosponsor>True</isOriginalCosponsor>
        <firstName>Al</firstName>
        <sponsorshipDate>2017-05-25</sponsorshipDate>
        <lastName>Franken</lastName>
      </item>
      <item>
        <identifiers>
          <lisID>2182</lisID>
          <gpoId />
          <bioguideId>W000817</bioguideId>
        </identifiers>
        <sponsorshipWithdrawnDate />
        <party>D</party>
        <bioguideId>W000817</bioguideId>
        <state>MA</state>
        <middleName>A.</middleName>
        <fullName>Sen. Warren, Elizabeth [D-MA]</fullName>
        <isOriginalCosponsor>True</isOriginalCosponsor>
        <firstName>Elizabeth</firstName>
        <sponsorshipDate>2017-05-25</sponsorshipDate>
        <lastName>Warren</lastName>
      </item>
      <item>
        <identifiers>
          <bioguideId>B001267</bioguideId>
          <lisID>1965</lisID>
          <gpoId>8302</gpoId>
        </identifiers>
        <sponsorshipWithdrawnDate />
        <party>D</party>
        <bioguideId>B001267</bioguideId>
        <state>CO</state>
        <middleName>F.</middleName>
        <fullName>Sen. Bennet, Michael F. [D-CO]</fullName>
        <isOriginalCosponsor>True</isOriginalCosponsor>
        <firstName>Michael</firstName>
        <sponsorshipDate>2017-05-25</sponsorshipDate>
        <lastName>Bennet</lastName>
      </item>
      <item>
        <identifiers>
          <bioguideId>H001046</bioguideId>
          <lisID>1937</lisID>
          <gpoId>8056</gpoId>
        </identifiers>
        <sponsorshipWithdrawnDate />
        <party>D</party>
        <bioguideId>H001046</bioguideId>
        <state>NM</state>
        <middleName />
        <fullName>Sen. Heinrich, Martin [D-NM]</fullName>
        <isOriginalCosponsor>True</isOriginalCosponsor>
        <firstName>Martin</firstName>
        <sponsorshipDate>2017-05-25</sponsorshipDate>
        <lastName>Heinrich</lastName>
      </item>
      <item>
        <identifiers>
          <bioguideId>S000033</bioguideId>
          <lisID>1010</lisID>
          <gpoId>8270</gpoId>
        </identifiers>
        <sponsorshipWithdrawnDate />
        <party>I</party>
        <bioguideId>S000033</bioguideId>
        <state>VT</state>
        <middleName />
        <fullName>Sen. Sanders, Bernard [I-VT]</fullName>
        <isOriginalCosponsor>True</isOriginalCosponsor>
        <firstName>BERNARD</firstName>
        <sponsorshipDate>2017-05-25</sponsorshipDate>
        <lastName>SANDERS</lastName>
      </item>
      <item>
        <identifiers>
          <gpoId>8258</gpoId>
          <lisID>1829</lisID>
          <bioguideId>T000464</bioguideId>
        </identifiers>
        <sponsorshipWithdrawnDate />
        <party>D</party>
        <bioguideId>T000464</bioguideId>
        <state>MT</state>
        <middleName />
        <fullName>Sen. Tester, Jon [D-MT]</fullName>
        <isOriginalCosponsor>True</isOriginalCosponsor>
        <firstName>Jon</firstName>
        <sponsorshipDate>2017-05-25</sponsorshipDate>
        <lastName>Tester</lastName>
      </item>
      <item>
        <identifiers>
          <gpoId>8269</gpoId>
          <bioguideId>W000805</bioguideId>
          <lisID>1897</lisID>
        </identifiers>
        <sponsorshipWithdrawnDate />
        <party>D</party>
        <bioguideId>W000805</bioguideId>
        <state>VA</state>
        <middleName>R.</middleName>
        <fullName>Sen. Warner, Mark R. [D-VA]</fullName>
        <isOriginalCosponsor>True</isOriginalCosponsor>
        <firstName>Mark</firstName>
        <sponsorshipDate>2017-05-25</sponsorshipDate>
        <lastName>Warner</lastName>
      </item>
      <item>
        <identifiers>
          <lisID>172</lisID>
          <gpoId>8288</gpoId>
          <bioguideId>C000127</bioguideId>
        </identifiers>
        <sponsorshipWithdrawnDate />
        <party>D</party>
        <bioguideId>C000127</bioguideId>
        <state>WA</state>
        <middleName />
        <fullName>Sen. Cantwell, Maria [D-WA]</fullName>
        <isOriginalCosponsor>True</isOriginalCosponsor>
        <firstName>MARIA</firstName>
        <sponsorshipDate>2017-05-25</sponsorshipDate>
        <lastName>CANTWELL</lastName>
      </item>
      <item>
        <identifiers>
          <bioguideId>B001277</bioguideId>
          <lisID>2076</lisID>
          <gpoId>8332</gpoId>
        </identifiers>
        <sponsorshipWithdrawnDate />
        <party>D</party>
        <bioguideId>B001277</bioguideId>
        <state>CT</state>
        <middleName />
        <fullName>Sen. Blumenthal, Richard [D-CT]</fullName>
        <isOriginalCosponsor>True</isOriginalCosponsor>
        <firstName>Richard</firstName>
        <sponsorshipDate>2017-05-25</sponsorshipDate>
        <lastName>Blumenthal</lastName>
      </item>
      <item>
        <identifiers>
          <gpoId>8237</gpoId>
          <bioguideId>M001111</bioguideId>
          <lisID>1409</lisID>
        </identifiers>
        <sponsorshipWithdrawnDate />
        <party>D</party>
        <bioguideId>M001111</bioguideId>
        <state>WA</state>
        <middleName />
        <fullName>Sen. Murray, Patty [D-WA]</fullName>
        <isOriginalCosponsor>True</isOriginalCosponsor>
        <firstName>PATTY</firstName>
        <sponsorshipDate>2017-05-25</sponsorshipDate>
        <lastName>MURRAY</lastName>
      </item>
      <item>
        <identifiers>
          <bioguideId>S000148</bioguideId>
          <gpoId>8279</gpoId>
          <lisID>1036</lisID>
        </identifiers>
        <sponsorshipWithdrawnDate />
        <party>D</party>
        <bioguideId>S000148</bioguideId>
        <state>NY</state>
        <middleName>E.</middleName>
        <fullName>Sen. Schumer, Charles E. [D-NY]</fullName>
        <isOriginalCosponsor>True</isOriginalCosponsor>
        <firstName>CHARLES</firstName>
        <sponsorshipDate>2017-05-25</sponsorshipDate>
        <lastName>SCHUMER</lastName>
      </item>
      <item>
        <identifiers>
          <lisID>1866</lisID>
          <gpoId>8336</gpoId>
          <bioguideId>G000555</bioguideId>
        </identifiers>
        <sponsorshipWithdrawnDate />
        <party>D</party>
        <bioguideId>G000555</bioguideId>
        <state>NY</state>
        <middleName>E.</middleName>
        <fullName>Sen. Gillibrand, Kirsten E. [D-NY]</fullName>
        <isOriginalCosponsor>True</isOriginalCosponsor>
        <firstName>Kirsten</firstName>
        <sponsorshipDate>2017-05-25</sponsorshipDate>
        <lastName>Gillibrand</lastName>
      </item>
      <item>
        <identifiers>
          <bioguideId>N000032</bioguideId>
          <gpoId>8236</gpoId>
          <lisID>859</lisID>
        </identifiers>
        <sponsorshipWithdrawnDate />
        <party>D</party>
        <bioguideId>N000032</bioguideId>
        <state>FL</state>
        <middleName>WILLIAM</middleName>
        <fullName>Sen. Nelson, Bill [D-FL]</fullName>
        <isOriginalCosponsor>True</isOriginalCosponsor>
        <firstName>CLARENCE</firstName>
        <sponsorshipDate>2017-05-25</sponsorshipDate>
        <lastName>NELSON</lastName>
      </item>
      <item>
        <identifiers>
          <bioguideId>D000607</bioguideId>
          <lisID>1850</lisID>
          <gpoId>7941</gpoId>
        </identifiers>
        <sponsorshipWithdrawnDate />
        <party>D</party>
        <bioguideId>D000607</bioguideId>
        <state>IN</state>
        <middleName />
        <fullName>Sen. Donnelly, Joe [D-IN]</fullName>
        <isOriginalCosponsor>True</isOriginalCosponsor>
        <firstName>Joe</firstName>
        <sponsorshipDate>2017-05-25</sponsorshipDate>
        <lastName>Donnelly</lastName>
      </item>
      <item>
        <identifiers>
          <lisID>1925</lisID>
          <gpoId>7964</gpoId>
          <bioguideId>C001075</bioguideId>
        </identifiers>
        <sponsorshipWithdrawnDate />
        <party>R</party>
        <bioguideId>C001075</bioguideId>
        <state>LA</state>
        <middleName />
        <fullName>Sen. Cassidy, Bill [R-LA]</fullName>
        <isOriginalCosponsor>True</isOriginalCosponsor>
        <firstName>Bill</firstName>
        <sponsorshipDate>2017-05-25</sponsorshipDate>
        <lastName>Cassidy</lastName>
      </item>
      <item>
        <identifiers>
          <bioguideId>P000595</bioguideId>
          <gpoId>7994</gpoId>
          <lisID>1929</lisID>
        </identifiers>
        <sponsorshipWithdrawnDate />
        <party>D</party>
        <bioguideId>P000595</bioguideId>
        <state>MI</state>
        <middleName>C.</middleName>
        <fullName>Sen. Peters, Gary C. [D-MI]</fullName>
        <isOriginalCosponsor>True</isOriginalCosponsor>
        <firstName>Gary</firstName>
        <sponsorshipDate>2017-05-25</sponsorshipDate>
        <lastName>Peters</lastName>
      </item>
      <item>
        <identifiers>
          <lisID>179</lisID>
          <gpoId>8283</gpoId>
          <bioguideId>C000174</bioguideId>
        </identifiers>
        <sponsorshipWithdrawnDate />
        <party>D</party>
        <bioguideId>C000174</bioguideId>
        <state>DE</state>
        <middleName>R.</middleName>
        <fullName>Sen. Carper, Thomas R. [D-DE]</fullName>
        <isOriginalCosponsor>True</isOriginalCosponsor>
        <firstName>THOMAS</firstName>
        <sponsorshipDate>2017-05-25</sponsorshipDate>
        <lastName>CARPER</lastName>
      </item>
      <item>
        <identifiers>
          <bioguideId>M001183</bioguideId>
          <lisID>1983</lisID>
          <gpoId>8256</gpoId>
        </identifiers>
        <sponsorshipWithdrawnDate />
        <party>D</party>
        <bioguideId>M001183</bioguideId>
        <state>WV</state>
        <middleName />
        <fullName>Sen. Manchin, Joe, III [D-WV]</fullName>
        <isOriginalCosponsor>True</isOriginalCosponsor>
        <firstName>Joe</firstName>
        <sponsorshipDate>2017-05-25</sponsorshipDate>
        <lastName>Manchin</lastName>
      </item>
      <item>
        <identifiers>
          <bioguideId>V000128</bioguideId>
          <lisID>1729</lisID>
          <gpoId>7983</gpoId>
        </identifiers>
        <sponsorshipWithdrawnDate />
        <party>D</party>
        <bioguideId>V000128</bioguideId>
        <state>MD</state>
        <middleName />
        <fullName>Sen. Van Hollen, Chris [D-MD]</fullName>
        <isOriginalCosponsor>True</isOriginalCosponsor>
        <firstName>Chris</firstName>
        <sponsorshipDate>2017-05-25</sponsorshipDate>
        <lastName>Van Hollen</lastName>
      </item>
      <item>
        <identifiers>
          <lisID>2301</lisID>
          <gpoId />
          <bioguideId>H001075</bioguideId>
        </identifiers>
        <sponsorshipWithdrawnDate />
        <party>D</party>
        <bioguideId>H001075</bioguideId>
        <state>CA</state>
        <middleName>D.</middleName>
        <fullName>Sen. Harris, Kamala D. [D-CA]</fullName>
        <isOriginalCosponsor>True</isOriginalCosponsor>
        <firstName>Kamala</firstName>
        <sponsorshipDate>2017-05-25</sponsorshipDate>
        <lastName>Harris</lastName>
      </item>
      <item>
        <identifiers>
          <gpoId>8282</gpoId>
          <lisID>1828</lisID>
          <bioguideId>C001070</bioguideId>
        </identifiers>
        <sponsorshipWithdrawnDate />
        <party>D</party>
        <bioguideId>C001070</bioguideId>
        <state>PA</state>
        <middleName />
        <fullName>Sen. Casey, Robert P., Jr. [D-PA]</fullName>
        <isOriginalCosponsor>True</isOriginalCosponsor>
        <firstName>Bob</firstName>
        <sponsorshipDate>2017-05-25</sponsorshipDate>
        <lastName>Casey</lastName>
      </item>
      <item>
        <identifiers>
          <gpoId>8289</gpoId>
          <bioguideId>C000880</bioguideId>
          <lisID>250</lisID>
        </identifiers>
        <sponsorshipWithdrawnDate />
        <party>R</party>
        <bioguideId>C000880</bioguideId>
        <state>ID</state>
        <middleName>D.</middleName>
        <fullName>Sen. Crapo, Mike [R-ID]</fullName>
        <isOriginalCosponsor>True</isOriginalCosponsor>
        <firstName>MICHAEL</firstName>
        <sponsorshipDate>2017-05-25</sponsorshipDate>
        <lastName>CRAPO</lastName>
      </item>
      <item>
        <identifiers>
          <lisID>2123</lisID>
          <gpoId />
          <bioguideId>D000622</bioguideId>
        </identifiers>
        <sponsorshipWithdrawnDate />
        <party>D</party>
        <bioguideId>D000622</bioguideId>
        <state>IL</state>
        <middleName />
        <fullName>Sen. Duckworth, Tammy [D-IL]</fullName>
        <isOriginalCosponsor>True</isOriginalCosponsor>
        <firstName>Tammy</firstName>
        <sponsorshipDate>2017-05-25</sponsorshipDate>
        <lastName>Duckworth</lastName>
      </item>
      <item>
        <identifiers>
          <bioguideId>D000618</bioguideId>
          <lisID>2138</lisID>
          <gpoId />
        </identifiers>
        <sponsorshipWithdrawnDate />
        <party>R</party>
        <bioguideId>D000618</bioguideId>
        <state>MT</state>
        <middleName />
        <fullName>Sen. Daines, Steve [R-MT]</fullName>
        <isOriginalCosponsor>True</isOriginalCosponsor>
        <firstName>Steve</firstName>
        <sponsorshipDate>2017-05-25</sponsorshipDate>
        <lastName>Daines</lastName>
      </item>
      <item>
        <identifiers>
          <bioguideId>H001076</bioguideId>
          <lisID>2302</lisID>
          <gpoId />
        </identifiers>
        <sponsorshipWithdrawnDate />
        <party>D</party>
        <bioguideId>H001076</bioguideId>
        <state>NH</state>
        <middleName>Wood</middleName>
        <fullName>Sen. Hassan, Margaret Wood [D-NH]</fullName>
        <isOriginalCosponsor>True</isOriginalCosponsor>
        <firstName>Margaret</firstName>
        <sponsorshipDate>2017-05-25</sponsorshipDate>
        <lastName>Hassan</lastName>
      </item>
      <item>
        <identifiers>
          <lisID>1863</lisID>
          <gpoId>8060</gpoId>
          <bioguideId>H001041</bioguideId>
        </identifiers>
        <sponsorshipWithdrawnDate />
        <party>R</party>
        <bioguideId>H001041</bioguideId>
        <state>NV</state>
        <middleName />
        <fullName>Sen. Heller, Dean [R-NV]</fullName>
        <isOriginalCosponsor>True</isOriginalCosponsor>
        <firstName>Dean</firstName>
        <sponsorshipDate>2017-05-25</sponsorshipDate>
        <lastName>Heller</lastName>
      </item>
    </cosponsors>
    <billNumber>1287</billNumber>
    <summaries>
      <billSummaries>
        <item>
          <lastSummaryUpdateDate>2017-07-25T15:42:16Z</lastSummaryUpdateDate>
          <updateDate>2017-05-25T04:00:00Z</updateDate>
          <name>Introduced in Senate</name>
          <text><![CDATA[<p><strong>Freedom for Americans to Travel to Cuba Act of 2017</strong></p> <p>This bill states that: (1) the President may not prohibit or otherwise restrict travel to or from Cuba by U.S. citizens or legal residents, or any of the transactions incident to such travel, including banking transactions; and (2) any law, regulation, or policy in effect on the date of enactment of this bill that prohibits or otherwise restricts such travel or transactions incident to such travel shall cease to have any force or effect. </p> <p>Nothing in this bill may be construed to limit the President's authority to restrict such travel or any transaction incident to such travel if the President determines that such restriction is necessary to protect: (1) U.S. national security, or (2) the health or safety of U.S. citizens or legal residents resulting from traveling to or from Cuba.</p> <p>Prior to restricting travel to Cuba, the President shall submit a written justification to Congress.</p>]]></text>
          <actionDesc>Introduced in Senate</actionDesc>
          <actionDate>2017-05-25</actionDate>
          <versionCode>00</versionCode>
        </item>
      </billSummaries>
    </summaries>
    <committeeReports />
    <introducedDate>2017-05-25</introducedDate>
    <updateDate>2017-07-28T10:38:01Z</updateDate>
    <actions>
      <actionTypeCounts>
        <referredToCommittee>1</referredToCommittee>
        <introducedInSenate>1</introducedInSenate>
      </actionTypeCounts>
      <actionByCounts>
        <senate>2</senate>
      </actionByCounts>
      <item>
        <actionDate>2017-05-25</actionDate>
        <committee>
          <systemCode>ssfr00</systemCode>
          <name>Foreign Relations Committee</name>
        </committee>
        <links>
          <link>
            <name>S3222-3223</name>
            <url>https://www.congress.gov/congressional-record/volume-163/senate-section/page/S3222-3223</url>
          </link>
        </links>
        <sourceSystem>
          <code>0</code>
          <name>Senate</name>
        </sourceSystem>
        <text>Read twice and referred to the Committee on Foreign Relations. (Sponsor introductory remarks on measure: CR S3222-3223)</text>
        <type>IntroReferral</type>
      </item>
      <item>
        <actionCode>10000</actionCode>
        <text>Introduced in Senate</text>
        <committee />
        <sourceSystem>
          <code>9</code>
          <name>Library of Congress</name>
        </sourceSystem>
        <actionDate>2017-05-25</actionDate>
        <type>IntroReferral</type>
        <links />
      </item>
    </actions>
    <sponsors>
      <item>
        <bioguideId>F000444</bioguideId>
        <middleName />
        <lastName>FLAKE</lastName>
        <identifiers>
          <gpoId>7803</gpoId>
          <bioguideId>F000444</bioguideId>
          <lisID>1633</lisID>
        </identifiers>
        <party>R</party>
        <state>AZ</state>
        <firstName>JEFF</firstName>
        <fullName>Sen. Flake, Jeff [R-AZ]</fullName>
        <byRequestType />
      </item>
    </sponsors>
    <cboCostEstimates />
    <titles>
      <item>
        <chamberCode />
        <chamberName />
        <parentTitleType />
        <titleType>(Extracted from GPO) Short Titles as Introduced</titleType>
        <title>Freedom for Americans to Travel to Cuba Act of 2017</title>
      </item>
      <item>
        <chamberCode />
        <chamberName />
        <parentTitleType />
        <titleType>Short Titles as Introduced</titleType>
        <title>Freedom for Americans to Travel to Cuba Act of 2017</title>
      </item>
      <item>
        <chamberCode />
        <chamberName />
        <parentTitleType />
        <titleType>Official Title as Introduced</titleType>
        <title>A bill to allow United States citizens and legal residents to travel between the United States and Cuba.</title>
      </item>
      <item>
        <chamberCode />
        <chamberName />
        <parentTitleType />
        <titleType>Display Title</titleType>
        <title>Freedom for Americans to Travel to Cuba Act of 2017</title>
      </item>
    </titles>
    <calendarNumbers />
    <title>Freedom for Americans to Travel to Cuba Act of 2017</title>
    <createDate>2017-05-26T00:41:40Z</createDate>
    <laws />
    <committees>
      <billCommittees>
        <item>
          <chamber>Senate</chamber>
          <name>Foreign Relations Committee</name>
          <systemCode>ssfr00</systemCode>
          <activities>
            <item>
              <date>2017-05-25T21:30:37Z</date>
              <name>Referred to</name>
            </item>
          </activities>
          <type>Standing</type>
          <subcommittees />
        </item>
      </billCommittees>
    </committees>
    <latestAction>
      <actionDate>2017-05-25</actionDate>
      <links />
      <text>Read twice and referred to the Committee on Foreign Relations. (Sponsor introductory remarks on measure: CR S3222-3223)</text>
    </latestAction>
    <originChamber>Senate</originChamber>
    <congress>115</congress>
    <billType>S</billType>
    <amendments />
    <policyArea>
      <name>International Affairs</name>
    </policyArea>
    <relatedBills>
      <item>
        <number>351</number>
        <latestAction>
          <text>Referred to the Subcommittee on the Western Hemisphere.</text>
          <actionDate>2017-02-16</actionDate>
        </latestAction>
        <type>HR</type>
        <latestTitle>Freedom to Travel to Cuba Act of 2017</latestTitle>
        <relationshipDetails>
          <item>
            <identifiedBy>CRS</identifiedBy>
            <type>Related bill</type>
          </item>
        </relationshipDetails>
        <congress>115</congress>
      </item>
    </relatedBills>
    <subjects>
      <billSubjects>
        <legislativeSubjects />
        <policyArea>
          <name>International Affairs</name>
        </policyArea>
      </billSubjects>
    </subjects>
    <version>1.0.0</version>
    <notes />
  </bill>
  <dublinCore xmlns:dc="http://purl.org/dc/elements/1.1/">
    <dc:format>text/xml</dc:format>
    <dc:language>EN</dc:language>
    <dc:rights>Pursuant to Title 17 Section 105 of the United States Code, this file is not subject to copyright protection and is in the public domain.</dc:rights>
    <dc:contributor>Congressional Research Service, Library of Congress</dc:contributor>
    <dc:description>This file contains bill summaries and statuses for federal legislation. A bill summary describes the most significant provisions of a piece of legislation and details the effects the legislative text may have on current law and federal programs. Bill summaries are authored by the Congressional Research Service (CRS) of the Library of Congress. As stated in Public Law 91-510 (2 USC 166 (d)(6)), one of the duties of CRS is "to prepare summaries and digests of bills and resolutions of a public general nature introduced in the Senate or House of Representatives". For more information, refer to the User Guide that accompanies this file.</dc:description>
  </dublinCore>
</billStatus>

