<?xml version="1.0" encoding="UTF-8"?>
<billStatus>
  <bill>
    <committeeReports />
    <createDate>2017-06-21T07:26:40Z</createDate>
    <summaries>
      <billSummaries />
    </summaries>
    <amendments />
    <billType>S</billType>
    <updateDate>2017-07-07T04:28:26Z</updateDate>
    <introducedDate>2017-06-20</introducedDate>
    <actions>
      <item>
        <actionDate>2017-06-20</actionDate>
        <committee>
          <systemCode>ssfr00</systemCode>
          <name>Foreign Relations Committee</name>
        </committee>
        <links>
          <link>
            <url>https://www.congress.gov/congressional-record/volume-163/senate-section/page/S3652</url>
            <name>S3652</name>
          </link>
        </links>
        <sourceSystem>
          <code>0</code>
          <name>Senate</name>
        </sourceSystem>
        <text>Read twice and referred to the Committee on Foreign Relations. (text of measure as introduced: CR S3652)</text>
        <type>IntroReferral</type>
      </item>
      <item>
        <text>Introduced in Senate</text>
        <links />
        <sourceSystem>
          <code>9</code>
          <name>Library of Congress</name>
        </sourceSystem>
        <actionCode>10000</actionCode>
        <committee />
        <actionDate>2017-06-20</actionDate>
        <type>IntroReferral</type>
      </item>
      <actionTypeCounts>
        <referredToCommittee>1</referredToCommittee>
        <introducedInSenate>1</introducedInSenate>
      </actionTypeCounts>
      <actionByCounts>
        <senate>2</senate>
      </actionByCounts>
    </actions>
    <congress>115</congress>
    <latestAction>
      <text>Read twice and referred to the Committee on Foreign Relations. (text of measure as introduced: CR S3652)</text>
      <links />
      <actionDate>2017-06-20</actionDate>
    </latestAction>
    <recordedVotes />
    <relatedBills>
      <item>
        <number>882</number>
        <latestTitle>North American Development Bank Improvement and General Capital Increase Authorization Act of 2017</latestTitle>
        <congress>115</congress>
        <relationshipDetails>
          <item>
            <identifiedBy>CRS</identifiedBy>
            <type>Related bill</type>
          </item>
        </relationshipDetails>
        <type>HR</type>
        <latestAction>
          <actionDate>2017-02-06</actionDate>
          <text>Referred to the House Committee on Financial Services.</text>
        </latestAction>
      </item>
    </relatedBills>
    <notes />
    <billNumber>1385</billNumber>
    <cboCostEstimates />
    <version>1.0.0</version>
    <laws />
    <cosponsors>
      <item>
        <fullName>Sen. Feinstein, Dianne [D-CA]</fullName>
        <sponsorshipDate>2017-06-20</sponsorshipDate>
        <firstName>DIANNE</firstName>
        <bioguideId>F000062</bioguideId>
        <party>D</party>
        <lastName>FEINSTEIN</lastName>
        <isOriginalCosponsor>True</isOriginalCosponsor>
        <middleName />
        <sponsorshipWithdrawnDate />
        <identifiers>
          <lisID>1332</lisID>
          <gpoId>8338</gpoId>
          <bioguideId>F000062</bioguideId>
        </identifiers>
        <state>CA</state>
      </item>
    </cosponsors>
    <originChamber>Senate</originChamber>
    <sponsors>
      <item>
        <middleName />
        <party>R</party>
        <state>TX</state>
        <identifiers>
          <bioguideId>C001056</bioguideId>
          <lisID>1692</lisID>
          <gpoId>8295</gpoId>
        </identifiers>
        <lastName>Cornyn</lastName>
        <byRequestType />
        <fullName>Sen. Cornyn, John [R-TX]</fullName>
        <bioguideId>C001056</bioguideId>
        <firstName>John</firstName>
      </item>
    </sponsors>
    <policyArea>
      <name>International Affairs</name>
    </policyArea>
    <calendarNumbers />
    <title>North American Development Bank Improvement Act of 2017</title>
    <subjects>
      <billSubjects>
        <policyArea>
          <name>International Affairs</name>
        </policyArea>
        <legislativeSubjects />
      </billSubjects>
    </subjects>
    <committees>
      <billCommittees>
        <item>
          <type>Standing</type>
          <systemCode>ssfr00</systemCode>
          <chamber>Senate</chamber>
          <subcommittees />
          <activities>
            <item>
              <name>Referred to</name>
              <date>2017-06-20T19:02:47Z</date>
            </item>
          </activities>
          <name>Foreign Relations Committee</name>
        </item>
      </billCommittees>
    </committees>
    <titles>
      <item>
        <chamberCode />
        <parentTitleType />
        <titleType>(Extracted from GPO) Short Titles as Introduced</titleType>
        <title>North American Development Bank Improvement Act of 2017</title>
        <chamberName />
      </item>
      <item>
        <chamberCode />
        <parentTitleType />
        <titleType>Short Titles as Introduced</titleType>
        <title>North American Development Bank Improvement Act of 2017</title>
        <chamberName />
      </item>
      <item>
        <chamberCode />
        <parentTitleType />
        <titleType>Official Title as Introduced</titleType>
        <title>A bill to provide for a general capital increase for the North American Development Bank, and for other purposes.</title>
        <chamberName />
      </item>
      <item>
        <chamberCode />
        <parentTitleType />
        <titleType>Display Title</titleType>
        <title>North American Development Bank Improvement Act of 2017</title>
        <chamberName />
      </item>
    </titles>
  </bill>
  <dublinCore xmlns:dc="http://purl.org/dc/elements/1.1/">
    <dc:format>text/xml</dc:format>
    <dc:language>EN</dc:language>
    <dc:rights>Pursuant to Title 17 Section 105 of the United States Code, this file is not subject to copyright protection and is in the public domain.</dc:rights>
    <dc:contributor>Congressional Research Service, Library of Congress</dc:contributor>
    <dc:description>This file contains bill summaries and statuses for federal legislation. A bill summary describes the most significant provisions of a piece of legislation and details the effects the legislative text may have on current law and federal programs. Bill summaries are authored by the Congressional Research Service (CRS) of the Library of Congress. As stated in Public Law 91-510 (2 USC 166 (d)(6)), one of the duties of CRS is "to prepare summaries and digests of bills and resolutions of a public general nature introduced in the Senate or House of Representatives". For more information, refer to the User Guide that accompanies this file.</dc:description>
  </dublinCore>
</billStatus>

