<?xml version="1.0" encoding="UTF-8"?>
<billStatus>
  <bill>
    <createDate>2017-03-10T05:16:37Z</createDate>
    <updateDate>2017-08-25T19:45:36Z</updateDate>
    <amendments />
    <title>Simon Wiesenthal Holocaust Education Assistance Act</title>
    <constitutionalAuthorityStatementText><![CDATA[<pre>From the Congressional Record Online through the Government Publishing Office [<a href='http://www.gpo.gov'>www.gpo.gov</a>]By Mrs. CAROLYN B. MALONEY of New York:H.R. 1474.Congress has the power to enact this legislation pursuantto the following:Article I, Section 8[Page H2020]</pre>]]></constitutionalAuthorityStatementText>
    <introducedDate>2017-03-09</introducedDate>
    <sponsors>
      <item>
        <firstName>CAROLYN</firstName>
        <fullName>Rep. Maloney, Carolyn B. [D-NY-12]</fullName>
        <bioguideId>M000087</bioguideId>
        <middleName>B.</middleName>
        <byRequestType />
        <party>D</party>
        <state>NY</state>
        <lastName>MALONEY</lastName>
        <district>12</district>
        <identifiers>
          <bioguideId>M000087</bioguideId>
          <gpoId>8075</gpoId>
          <lisID>729</lisID>
        </identifiers>
      </item>
    </sponsors>
    <notes />
    <billNumber>1474</billNumber>
    <cosponsors>
      <item>
        <lastName>Rosen</lastName>
        <identifiers>
          <bioguideId>R000608</bioguideId>
          <gpoId />
          <lisID>2339</lisID>
        </identifiers>
        <bioguideId>R000608</bioguideId>
        <state>NV</state>
        <party>D</party>
        <district>3</district>
        <sponsorshipWithdrawnDate />
        <isOriginalCosponsor>False</isOriginalCosponsor>
        <middleName />
        <fullName>Rep. Rosen, Jacky [D-NV-3]</fullName>
        <sponsorshipDate>2017-04-25</sponsorshipDate>
        <firstName>Jacky</firstName>
      </item>
      <item>
        <lastName>Deutch</lastName>
        <identifiers>
          <bioguideId>D000610</bioguideId>
          <gpoId>7891</gpoId>
          <lisID>1976</lisID>
        </identifiers>
        <bioguideId>D000610</bioguideId>
        <state>FL</state>
        <party>D</party>
        <district>22</district>
        <sponsorshipWithdrawnDate />
        <isOriginalCosponsor>False</isOriginalCosponsor>
        <middleName>E.</middleName>
        <fullName>Rep. Deutch, Theodore E. [D-FL-22]</fullName>
        <sponsorshipDate>2017-04-25</sponsorshipDate>
        <firstName>Theodore</firstName>
      </item>
      <item>
        <lastName>Rice</lastName>
        <identifiers>
          <bioguideId>R000602</bioguideId>
          <gpoId />
          <lisID>2262</lisID>
        </identifiers>
        <bioguideId>R000602</bioguideId>
        <state>NY</state>
        <party>D</party>
        <district>4</district>
        <sponsorshipWithdrawnDate />
        <isOriginalCosponsor>False</isOriginalCosponsor>
        <middleName>M.</middleName>
        <fullName>Rep. Rice, Kathleen M. [D-NY-4]</fullName>
        <sponsorshipDate>2017-04-25</sponsorshipDate>
        <firstName>Kathleen</firstName>
      </item>
      <item>
        <lastName>Boyle</lastName>
        <identifiers>
          <lisID>2267</lisID>
          <bioguideId>B001296</bioguideId>
          <gpoId />
        </identifiers>
        <bioguideId>B001296</bioguideId>
        <state>PA</state>
        <party>D</party>
        <district>13</district>
        <sponsorshipWithdrawnDate />
        <isOriginalCosponsor>False</isOriginalCosponsor>
        <middleName>F.</middleName>
        <fullName>Rep. Boyle, Brendan F. [D-PA-13]</fullName>
        <sponsorshipDate>2017-04-25</sponsorshipDate>
        <firstName>Brendan</firstName>
      </item>
      <item>
        <lastName>CROWLEY</lastName>
        <identifiers>
          <lisID>1604</lisID>
          <bioguideId>C001038</bioguideId>
          <gpoId>8068</gpoId>
        </identifiers>
        <bioguideId>C001038</bioguideId>
        <state>NY</state>
        <party>D</party>
        <district>14</district>
        <sponsorshipWithdrawnDate />
        <isOriginalCosponsor>False</isOriginalCosponsor>
        <middleName />
        <fullName>Rep. Crowley, Joseph [D-NY-14]</fullName>
        <sponsorshipDate>2017-04-25</sponsorshipDate>
        <firstName>JOSEPH</firstName>
      </item>
      <item>
        <lastName>Green</lastName>
        <identifiers>
          <lisID>1803</lisID>
          <bioguideId>G000553</bioguideId>
          <gpoId>8165</gpoId>
        </identifiers>
        <bioguideId>G000553</bioguideId>
        <state>TX</state>
        <party>D</party>
        <district>9</district>
        <sponsorshipWithdrawnDate />
        <isOriginalCosponsor>False</isOriginalCosponsor>
        <middleName />
        <fullName>Rep. Green, Al [D-TX-9]</fullName>
        <sponsorshipDate>2017-04-25</sponsorshipDate>
        <firstName>Al</firstName>
      </item>
      <item>
        <lastName>VELAZQUEZ</lastName>
        <identifiers>
          <lisID>1184</lisID>
          <bioguideId>V000081</bioguideId>
          <gpoId>8073</gpoId>
        </identifiers>
        <bioguideId>V000081</bioguideId>
        <state>NY</state>
        <party>D</party>
        <district>7</district>
        <sponsorshipWithdrawnDate />
        <isOriginalCosponsor>False</isOriginalCosponsor>
        <middleName>M.</middleName>
        <fullName>Rep. Velazquez, Nydia M. [D-NY-7]</fullName>
        <sponsorshipDate>2017-04-25</sponsorshipDate>
        <firstName>NYDIA</firstName>
      </item>
      <item>
        <lastName>LEVIN</lastName>
        <identifiers>
          <gpoId>7997</gpoId>
          <bioguideId>L000263</bioguideId>
          <lisID>683</lisID>
        </identifiers>
        <bioguideId>L000263</bioguideId>
        <state>MI</state>
        <party>D</party>
        <district>9</district>
        <sponsorshipWithdrawnDate />
        <isOriginalCosponsor>False</isOriginalCosponsor>
        <middleName>M.</middleName>
        <fullName>Rep. Levin, Sander M. [D-MI-9]</fullName>
        <sponsorshipDate>2017-04-25</sponsorshipDate>
        <firstName>SANDER</firstName>
      </item>
      <item>
        <lastName>Wasserman Schultz</lastName>
        <identifiers>
          <bioguideId>W000797</bioguideId>
          <gpoId>7892</gpoId>
          <lisID>1777</lisID>
        </identifiers>
        <bioguideId>W000797</bioguideId>
        <state>FL</state>
        <party>D</party>
        <district>23</district>
        <sponsorshipWithdrawnDate />
        <isOriginalCosponsor>False</isOriginalCosponsor>
        <middleName />
        <fullName>Rep. Wasserman Schultz, Debbie [D-FL-23]</fullName>
        <sponsorshipDate>2017-05-19</sponsorshipDate>
        <firstName>Debbie</firstName>
      </item>
      <item>
        <lastName>MCGOVERN</lastName>
        <identifiers>
          <gpoId>7968</gpoId>
          <lisID>1504</lisID>
          <bioguideId>M000312</bioguideId>
        </identifiers>
        <bioguideId>M000312</bioguideId>
        <state>MA</state>
        <party>D</party>
        <district>2</district>
        <sponsorshipWithdrawnDate />
        <isOriginalCosponsor>False</isOriginalCosponsor>
        <middleName>P.</middleName>
        <fullName>Rep. McGovern, James P. [D-MA-2]</fullName>
        <sponsorshipDate>2017-05-19</sponsorshipDate>
        <firstName>JAMES</firstName>
      </item>
      <item>
        <lastName>Norcross</lastName>
        <identifiers>
          <bioguideId>N000188</bioguideId>
          <gpoId />
          <lisID>2202</lisID>
        </identifiers>
        <bioguideId>N000188</bioguideId>
        <state>NJ</state>
        <party>D</party>
        <district>1</district>
        <sponsorshipWithdrawnDate />
        <isOriginalCosponsor>False</isOriginalCosponsor>
        <middleName />
        <fullName>Rep. Norcross, Donald [D-NJ-1]</fullName>
        <sponsorshipDate>2017-06-20</sponsorshipDate>
        <firstName>Donald</firstName>
      </item>
      <item>
        <lastName>ESHOO</lastName>
        <identifiers>
          <bioguideId>E000215</bioguideId>
          <gpoId>7819</gpoId>
          <lisID>355</lisID>
        </identifiers>
        <bioguideId>E000215</bioguideId>
        <state>CA</state>
        <party>D</party>
        <district>18</district>
        <sponsorshipWithdrawnDate />
        <isOriginalCosponsor>False</isOriginalCosponsor>
        <middleName>G.</middleName>
        <fullName>Rep. Eshoo, Anna G. [D-CA-18]</fullName>
        <sponsorshipDate>2017-08-25</sponsorshipDate>
        <firstName>ANNA</firstName>
      </item>
      <item>
        <lastName>DEFAZIO</lastName>
        <identifiers>
          <lisID>279</lisID>
          <bioguideId>D000191</bioguideId>
          <gpoId>8117</gpoId>
        </identifiers>
        <bioguideId>D000191</bioguideId>
        <state>OR</state>
        <party>D</party>
        <district>4</district>
        <sponsorshipWithdrawnDate />
        <isOriginalCosponsor>False</isOriginalCosponsor>
        <middleName>A.</middleName>
        <fullName>Rep. DeFazio, Peter A. [D-OR-4]</fullName>
        <sponsorshipDate>2017-08-25</sponsorshipDate>
        <firstName>PETER</firstName>
      </item>
    </cosponsors>
    <originChamber>House</originChamber>
    <subjects>
      <billSubjects>
        <policyArea>
          <name>Education</name>
        </policyArea>
        <legislativeSubjects>
          <item>
            <name>Education programs funding</name>
          </item>
          <item>
            <name>Elementary and secondary education</name>
          </item>
          <item>
            <name>Public contracts and procurement</name>
          </item>
          <item>
            <name>Religion</name>
          </item>
          <item>
            <name>Social work, volunteer service, charitable organizations</name>
          </item>
          <item>
            <name>War crimes, genocide, crimes against humanity</name>
          </item>
          <item>
            <name>World history</name>
          </item>
        </legislativeSubjects>
      </billSubjects>
    </subjects>
    <committeeReports />
    <congress>115</congress>
    <actions>
      <item>
        <links />
        <sourceSystem>
          <code>2</code>
          <name>House floor actions</name>
        </sourceSystem>
        <actionCode>H11100</actionCode>
        <actionDate>2017-03-09</actionDate>
        <text>Referred to the House Committee on Education and the Workforce.</text>
        <type>IntroReferral</type>
        <committee>
          <name>Education and the Workforce Committee</name>
          <systemCode>hsed00</systemCode>
        </committee>
      </item>
      <item>
        <links />
        <sourceSystem>
          <code>9</code>
          <name>Library of Congress</name>
        </sourceSystem>
        <actionCode>Intro-H</actionCode>
        <actionDate>2017-03-09</actionDate>
        <text>Introduced in House</text>
        <type>IntroReferral</type>
        <committee />
      </item>
      <item>
        <links />
        <sourceSystem>
          <code>9</code>
          <name>Library of Congress</name>
        </sourceSystem>
        <actionCode>1000</actionCode>
        <actionDate>2017-03-09</actionDate>
        <text>Introduced in House</text>
        <type>IntroReferral</type>
        <committee />
      </item>
      <actionTypeCounts>
        <billReferrals>1</billReferrals>
        <introducedInTheHouse>1</introducedInTheHouse>
        <introducedInHouse>1</introducedInHouse>
      </actionTypeCounts>
      <actionByCounts>
        <houseOfRepresentatives>3</houseOfRepresentatives>
      </actionByCounts>
    </actions>
    <titles>
      <item>
        <chamberCode />
        <titleType>(Extracted from GPO) Short Titles as Introduced</titleType>
        <title>Simon Wiesenthal Holocaust Education Assistance Act</title>
        <parentTitleType />
        <chamberName />
      </item>
      <item>
        <chamberCode />
        <titleType>Short Titles as Introduced</titleType>
        <title>Simon Wiesenthal Holocaust Education Assistance Act</title>
        <parentTitleType />
        <chamberName />
      </item>
      <item>
        <chamberCode />
        <titleType>Official Title as Introduced</titleType>
        <title>To authorize the Secretary of Education to award grants to educational organizations to carry out educational programs about the Holocaust.</title>
        <parentTitleType />
        <chamberName />
      </item>
      <item>
        <chamberCode />
        <titleType>Display Title</titleType>
        <title>Simon Wiesenthal Holocaust Education Assistance Act</title>
        <parentTitleType />
        <chamberName />
      </item>
    </titles>
    <recordedVotes />
    <relatedBills />
    <billType>HR</billType>
    <summaries>
      <billSummaries>
        <item>
          <actionDesc>Introduced in House</actionDesc>
          <versionCode>00</versionCode>
          <updateDate>2017-03-09T05:00:00Z</updateDate>
          <actionDate>2017-03-09</actionDate>
          <name>Introduced in House</name>
          <lastSummaryUpdateDate>2017-04-20T15:49:03Z</lastSummaryUpdateDate>
          <text><![CDATA[<p><b>Simon Wiesenthal Holocaust Education Assistance Act</b></p> <p>This bill amends the Elementary and Secondary Education Act of 1965 to authorize the Department of Education (ED) to award competitive grants to educational organizations to carry out proposed or existing Holocaust education programs.</p> <p>ED may contract with a nonprofit organization to encourage, accept, and administer private donations and gifts for funding the education programs.</p> <p>Grants may not be used to supplant nonfederal funds the grantees would otherwise have used for Holocaust education programs.</p>]]></text>
        </item>
      </billSummaries>
    </summaries>
    <cboCostEstimates />
    <policyArea>
      <name>Education</name>
    </policyArea>
    <committees>
      <billCommittees>
        <item>
          <chamber>House</chamber>
          <subcommittees />
          <activities>
            <item>
              <name>Referred to</name>
              <date>2017-03-09T15:07:00Z</date>
            </item>
          </activities>
          <name>Education and the Workforce Committee</name>
          <systemCode>hsed00</systemCode>
          <type>Standing</type>
        </item>
      </billCommittees>
    </committees>
    <calendarNumbers />
    <version>1.0.0</version>
    <latestAction>
      <text>Referred to the House Committee on Education and the Workforce.</text>
      <actionDate>2017-03-09</actionDate>
      <links />
    </latestAction>
    <laws />
  </bill>
  <dublinCore xmlns:dc="http://purl.org/dc/elements/1.1/">
    <dc:format>text/xml</dc:format>
    <dc:language>EN</dc:language>
    <dc:rights>Pursuant to Title 17 Section 105 of the United States Code, this file is not subject to copyright protection and is in the public domain.</dc:rights>
    <dc:contributor>Congressional Research Service, Library of Congress</dc:contributor>
    <dc:description>This file contains bill summaries and statuses for federal legislation. A bill summary describes the most significant provisions of a piece of legislation and details the effects the legislative text may have on current law and federal programs. Bill summaries are authored by the Congressional Research Service (CRS) of the Library of Congress. As stated in Public Law 91-510 (2 USC 166 (d)(6)), one of the duties of CRS is "to prepare summaries and digests of bills and resolutions of a public general nature introduced in the Senate or House of Representatives". For more information, refer to the User Guide that accompanies this file.</dc:description>
  </dublinCore>
</billStatus>

